hcli_hst/__init__.py
hcli_hst/__main__.py
hcli_hst/config.py
hcli_hst/hutils.py
hcli_hst/package.py
hcli_hst/cli/__init__.py
hcli_hst/cli/cli.py
hcli_hst/cli/config.py
hcli_hst/cli/logger.py
hcli_hst/cli/service.py
hcli_hst/cli/template.json
hcli_hst/cli/utils/__init__.py
hcli_hst/cli/utils/hutils.py
hcli_hst/data/hcli_hst.1
hcli_hst-0.1.1.dist-info/LICENSE.txt
hcli_hst-0.1.1.dist-info/METADATA
hcli_hst-0.1.1.dist-info/WHEEL
hcli_hst-0.1.1.dist-info/entry_points.txt
hcli_hst-0.1.1.dist-info/top_level.txt
hcli_hst-0.1.1.dist-info/RECORD
