Metadata-Version: 2.1
Name: hcli_hst
Version: 0.1.1
Summary: HCLI hst is a python package wrapper that contains an HCLI sample application (hst); hst is an HCLI SpaceTraders V2 API wrapper to help play the SpaceTraders API game.
Author-email: Jeff Michaud <cometaj2@proton.me>
License: Copyright (c) 2017 Jeff Michaud
Project-URL: Homepage, https://github.com/cometaj2/hcli_hst
Keywords: game,cli,client,server,connector,hypermedia,rest,generic,development
Classifier: Development Status :: 4 - Beta
Classifier: Intended Audience :: Developers
Classifier: Topic :: Software Development
Classifier: Programming Language :: Python :: 3.8
Classifier: Programming Language :: Python :: 3.9
Classifier: Programming Language :: Python :: 3.10
Classifier: Programming Language :: Python :: 3.11
Classifier: Programming Language :: Python :: 3.12
License-File: LICENSE.txt
Requires-Dist: requests==2.32.3
Requires-Dist: hcli-problem-details==0.2.0
